MANIFEST.in
README
VERSION
setup.cfg
setup.py
docs/default.cfg.sample
docs/license.txt
docs/release.howto
feed2mb/__init__.py
feed2mb/config.py
feed2mb/microblog.py
feed2mb/options.py
feed2mb/parsetime.py
feed2mb/readrss.py
feed2mb/shortener.py
feed2mb.egg-info/PKG-INFO
feed2mb.egg-info/SOURCES.txt
feed2mb.egg-info/dependency_links.txt
feed2mb.egg-info/entry_points.txt
feed2mb.egg-info/not-zip-safe
feed2mb.egg-info/top_level.txt
scripts/feed2mb