Metadata-Version: 1.0
Name: feed2mb
Version: 0.9.1
Summary: Publish your feed items to a microblog
Home-page: http://bitbucket.org/waltercruz/feed2mb/
Author: Walter Cruz
Author-email: walter@waltercruz.com
License: AGPL
Keywords: twitter feed identi.ca identica microblog wordpress
Platform: UNKNOWN
Classifier: Intended Audience :: Developers
Classifier: Programming Language :: Python
Classifier: Environment :: Console
Classifier: Development Status :: 5 - Production/Stable
